odoo8_addon_stock_mts_mto_rule-8.0.1.0.1-nspkg.pth
odoo_addons/stock_mts_mto_rule/README.rst
odoo_addons/stock_mts_mto_rule/__init__.py
odoo_addons/stock_mts_mto_rule/__openerp__.py
odoo_addons/stock_mts_mto_rule/data/stock_data.xml
odoo_addons/stock_mts_mto_rule/i18n/de.po
odoo_addons/stock_mts_mto_rule/i18n/es.po
odoo_addons/stock_mts_mto_rule/i18n/es_ES.po
odoo_addons/stock_mts_mto_rule/i18n/es_MX.po
odoo_addons/stock_mts_mto_rule/i18n/fr.po
odoo_addons/stock_mts_mto_rule/i18n/hr.po
odoo_addons/stock_mts_mto_rule/i18n/it.po
odoo_addons/stock_mts_mto_rule/i18n/pt_BR.po
odoo_addons/stock_mts_mto_rule/i18n/pt_PT.po
odoo_addons/stock_mts_mto_rule/i18n/ro.po
odoo_addons/stock_mts_mto_rule/i18n/ru.po
odoo_addons/stock_mts_mto_rule/i18n/sk.po
odoo_addons/stock_mts_mto_rule/i18n/sl.po
odoo_addons/stock_mts_mto_rule/i18n/stock_mts_mto_rule.pot
odoo_addons/stock_mts_mto_rule/i18n/tr_TR.po
odoo_addons/stock_mts_mto_rule/i18n/zh_CN.po
odoo_addons/stock_mts_mto_rule/model/__init__.py
odoo_addons/stock_mts_mto_rule/model/procurement.py
odoo_addons/stock_mts_mto_rule/model/rule.py
odoo_addons/stock_mts_mto_rule/model/warehouse.py
odoo_addons/stock_mts_mto_rule/static/description/icon.png
odoo_addons/stock_mts_mto_rule/tests/__init__.py
odoo_addons/stock_mts_mto_rule/tests/test_mto_mts_route.py
odoo_addons/stock_mts_mto_rule/view/pull_rule.xml
odoo_addons/stock_mts_mto_rule/view/warehouse.xml
odoo8_addon_stock_mts_mto_rule-8.0.1.0.1.dist-info/METADATA
odoo8_addon_stock_mts_mto_rule-8.0.1.0.1.dist-info/WHEEL
odoo8_addon_stock_mts_mto_rule-8.0.1.0.1.dist-info/namespace_packages.txt
odoo8_addon_stock_mts_mto_rule-8.0.1.0.1.dist-info/top_level.txt
odoo8_addon_stock_mts_mto_rule-8.0.1.0.1.dist-info/RECORD
